generify/__init__.py
generify/conftest.py
generify/encoder.py
generify/json_encoder.py
generify/test_generify.py
generify/version.py
generify-0.1.3.dist-info/LICENSE
generify-0.1.3.dist-info/METADATA
generify-0.1.3.dist-info/WHEEL
generify-0.1.3.dist-info/top_level.txt
generify-0.1.3.dist-info/RECORD
